accelerometer_test_v3/acc_driver.sv
module acc_driver(
    input   logic   clk12M,
    inout   logic   SDA,
    output  logic   SCL
);  

    reg clk400K = 0;
    reg [5:0] clk_cnt = 6'b000000;
    always_ff @(posedge clk12M) begin
        if(clk_cnt == 6'd14) begin
            clk400K = ~clk400K;
            clk_cnt = 6'd0;
        end else begin
            clk_cnt = clk_cnt + 1;
        end
    end

    always_comb begin
        SCL = clk400K;
    end
endmodule

accelerometer_test_v3/obj_dir/wave.vcd
$version Generated by VerilatedVcd $end
$date Wed May  6 21:09:53 2020
 $end
$timescale   1ns $end

 $scope module TOP $end
  $var wire  1 C SCL $end
  $var wire  1 ; SDA $end
  $var wire  1 3 clk12M $end
  $scope module acc_driver $end
   $var wire  1 C SCL $end
   $var wire  1 ; SDA $end
   $var wire  1 3 clk12M $end
   $var wire  1 # clk400K $end
   $var wire  6 + clk_cnt [5:0] $end
  $upscope $end
 $upscope $end
$enddefinitions $end


#0
0#
b000000 +
13
0;
0C
#1
#2
03
#3
#4
b000001 +
13
#5
#6
03
#7
#8
b000010 +
13
#9
#10
03
#11
#12
b000011 +
13
#13
#14
03
#15
#16
b000100 +
13
#17
#18
03
#19
#20
b000101 +
13
#21
#22
03
#23
#24
b000110 +
13
#25
#26
03
#27
#28
b000111 +
13
#29
#30
03
#31
#32
b001000 +
13
#33
#34
03
#35
#36
b001001 +
13
#37
#38
03
#39
#40
b001010 +
13
#41
#42
03
#43
#44
b001011 +
13
#45
#46
03
#47
#48
b001100 +
13
#49
#50
03
#51
#52
b001101 +
13
#53
#54
03
#55
#56
b001110 +
13
#57
#58
03
#59
#60
1#
b000000 +
13
1C
#61
#62
03
#63
#64
b000001 +
13
#65
#66
03
#67
#68
b000010 +
13
#69
#70
03
#71
#72
b000011 +
13
#73
#74
03
#75
#76
b000100 +
13
#77
#78
03
#79
#80
b000101 +
13
#81
#82
03
#83
#84
b000110 +
13
#85
#86
03
#87
#88
b000111 +
13
#89
#90
03
#91
#92
b001000 +
13
#93
#94
03
#95
#96
b001001 +
13
#97
#98
03
#99
#100
b001010 +
13
#101
#102
03
#103
#104
b001011 +
13
#105
#106
03
#107
#108
b001100 +
13
#109
#110
03
#111
#112
b001101 +
13
#113
#114
03
#115
#116
b001110 +
13
#117
#118
03
#119
#120
0#
b000000 +
13
0C
#121
#122
03
#123
#124
b000001 +
13
#125
#126
03
#127
#128
b000010 +
13
#129
#130
03
#131
#132
b000011 +
13
#133
#134
03
#135
#136
b000100 +
13
#137
#138
03
#139
#140
b000101 +
13
#141
#142
03
#143
#144
b000110 +
13
#145
#146
03
#147
#148
b000111 +
13
#149
#150
03
#151
#152
b001000 +
13
#153
#154
03
#155
#156
b001001 +
13
#157
#158
03
#159
#160
b001010 +
13
#161
#162
03
#163
#164
b001011 +
13
#165
#166
03
#167
#168
b001100 +
13
#169
#170
03
#171
#172
b001101 +
13
#173
#174
03
#175
#176
b001110 +
13
#177
#178
03
#179
#180
1#
b000000 +
13
1C
#181
#182
03
#183
#184
b000001 +
13
#185
#186
03
#187
#188
b000010 +
13
#189
#190
03
#191
#192
b000011 +
13
#193
#194
03
#195
#196
b000100 +
13
#197
#198
03
#199
#200
b000101 +
13
#201
#202
03
#203
#204
b000110 +
13
#205
#206
03
#207
#208
b000111 +
13
#209
#210
03
#211
#212
b001000 +
13
#213
#214
03
#215
#216
b001001 +
13
#217
#218
03
#219
#220
b001010 +
13
#221
#222
03
#223
#224
b001011 +
13
#225
#226
03
#227
#228
b001100 +
13
#229
#230
03
#231
#232
b001101 +
13
#233
#234
03
#235
#236
b001110 +
13
#237
#238
03
#239
#240
0#
b000000 +
13
0C
#241
#242
03
#243
#244
b000001 +
13
#245
#246
03
#247
#248
b000010 +
13
#249
#250
03
#251
#252
b000011 +
13
#253
#254
03
#255
#256
b000100 +
13
#257
#258
03
#259
#260
b000101 +
13
#261
#262
03
#263
#264
b000110 +
13
#265
#266
03
#267
#268
b000111 +
13
#269
#270
03
#271
#272
b001000 +
13
#273
#274
03
#275
#276
b001001 +
13
#277
#278
03
#279
#280
b001010 +
13
#281
#282
03
#283
#284
b001011 +
13
#285
#286
03
#287
#288
b001100 +
13
#289
#290
03
#291
#292
b001101 +
13
#293
#294
03
#295
#296
b001110 +
13
#297
#298
03
#299
#300
1#
b000000 +
13
1C
#301
#302
03
#303
#304
b000001 +
13
#305
#306
03
#307
#308
b000010 +
13
#309
#310
03
#311
#312
b000011 +
13
#313
#314
03
#315
#316
b000100 +
13
#317
#318
03
#319
#320
b000101 +
13
#321
#322
03
#323
#324
b000110 +
13
#325
#326
03
#327
#328
b000111 +
13
#329
#330
03
#331
#332
b001000 +
13
#333
#334
03
#335
#336
b001001 +
13
#337
#338
03
#339
#340
b001010 +
13
#341
#342
03
#343
#344
b001011 +
13
#345
#346
03
#347
#348
b001100 +
13
#349
#350
03
#351
#352
b001101 +
13
#353
#354
03
#355
#356
b001110 +
13
#357
#358
03
#359
#360
0#
b000000 +
13
0C
#361
#362
03
#363
#364
b000001 +
13
#365
#366
03
#367
#368
b000010 +
13
#369
#370
03
#371
#372
b000011 +
13
#373
#374
03
#375
#376
b000100 +
13
#377
#378
03
#379
#380
b000101 +
13
#381
#382
03
#383
#384
b000110 +
13
#385
#386
03
#387
#388
b000111 +
13
#389
#390
03
#391
#392
b001000 +
13
#393
#394
03
#395
#396
b001001 +
13
#397
#398
03
#399
#400
b001010 +
13
#401
#402
03
#403
#404
b001011 +
13
#405
#406
03
#407
#408
b001100 +
13
#409
#410
03
#411
#412
b001101 +
13
#413
#414
03
#415
#416
b001110 +
13
#417
#418
03
#419
#420
1#
b000000 +
13
1C
#421
#422
03
#423
#424
b000001 +
13
#425
#426
03
#427
#428
b000010 +
13
#429
#430
03
#431
#432
b000011 +
13
#433
#434
03
#435
#436
b000100 +
13
#437
#438
03
#439
#440
b000101 +
13
#441
#442
03
#443
#444
b000110 +
13
#445
#446
03
#447
#448
b000111 +
13
#449
#450
03
#451
#452
b001000 +
13
#453
#454
03
#455
#456
b001001 +
13
#457
#458
03
#459
#460
b001010 +
13
#461
#462
03
#463
#464
b001011 +
13
#465
#466
03
#467
#468
b001100 +
13
#469
#470
03
#471
#472
b001101 +
13
#473
#474
03
#475
#476
b001110 +
13
#477
#478
03
#479
#480
0#
b000000 +
13
0C
#481
#482
03
#483
#484
b000001 +
13
#485
#486
03
#487
#488
b000010 +
13
#489
#490
03
#491
#492
b000011 +
13
#493
#494
03
#495
#496
b000100 +
13
#497
#498
03
#499
#500
b000101 +
13
#501
#502
03
#503
#504
b000110 +
13
#505
#506
03
#507
#508
b000111 +
13
#509
#510
03
#511
#512
b001000 +
13
#513
#514
03
#515
#516
b001001 +
13
#517
#518
03
#519
#520
b001010 +
13
#521
#522
03
#523
#524
b001011 +
13
#525
#526
03
#527
#528
b001100 +
13
#529
#530
03
#531
#532
b001101 +
13
#533
#534
03
#535
#536
b001110 +
13
#537
#538
03
#539
#540
1#
b000000 +
13
1C
#541
#542
03
#543
#544
b000001 +
13
#545
#546
03
#547
#548
b000010 +
13
#549
#550
03
#551
#552
b000011 +
13
#553
#554
03
#555
#556
b000100 +
13
#557
#558
03
#559
#560
b000101 +
13
#561
#562
03
#563
#564
b000110 +
13
#565
#566
03
#567
#568
b000111 +
13
#569
#570
03
#571
#572
b001000 +
13
#573
#574
03
#575
#576
b001001 +
13
#577
#578
03
#579
#580
b001010 +
13
#581
#582
03
#583
#584
b001011 +
13
#585
#586
03
#587
#588
b001100 +
13
#589
#590
03
#591
#592
b001101 +
13
#593
#594
03
#595
#596
b001110 +
13
#597
#598
03
#599
#600
0#
b000000 +
13
0C
#601
#602
03
#603
#604
b000001 +
13
#605
#606
03
#607
#608
b000010 +
13
#609
#610
03
#611
#612
b000011 +
13
#613
#614
03
#615
#616
b000100 +
13
#617
#618
03
#619
#620
b000101 +
13
#621
#622
03
#623
#624
b000110 +
13
#625
#626
03
#627
#628
b000111 +
13
#629
#630
03
#631
#632
b001000 +
13
#633
#634
03
#635
#636
b001001 +
13
#637
#638
03
#639
#640
b001010 +
13
#641
#642
03
#643
#644
b001011 +
13
#645
#646
03
#647
#648
b001100 +
13
#649
#650
03
#651
#652
b001101 +
13
#653
#654
03
#655
#656
b001110 +
13
#657
#658
03
#659
#660
1#
b000000 +
13
1C
#661
#662
03
#663
#664
b000001 +
13
#665
#666
03
#667
#668
b000010 +
13
#669
#670
03
#671
#672
b000011 +
13
#673
#674
03
#675
#676
b000100 +
13
#677
#678
03
#679
#680
b000101 +
13
#681
#682
03
#683
#684
b000110 +
13
#685
#686
03
#687
#688
b000111 +
13
#689
#690
03
#691
#692
b001000 +
13
#693
#694
03
#695
#696
b001001 +
13
#697
#698
03
#699
#700
b001010 +
13
#701
#702
03
#703
#704
b001011 +
13
#705
#706
03
#707
#708
b001100 +
13
#709
#710
03
#711
#712
b001101 +
13
#713
#714
03
#715
#716
b001110 +
13
#717
#718
03
#719
#720
0#
b000000 +
13
0C
#721
#722
03
#723
#724
b000001 +
13
#725
#726
03
#727
#728
b000010 +
13
#729
#730
03
#731
#732
b000011 +
13
#733
#734
03
#735
#736
b000100 +
13
#737
#738
03
#739
#740
b000101 +
13
#741
#742
03
#743
#744
b000110 +
13
#745
#746
03
#747
#748
b000111 +
13
#749
#750
03
#751
#752
b001000 +
13
#753
#754
03
#755
#756
b001001 +
13
#757
#758
03
#759
#760
b001010 +
13
#761
#762
03
#763
#764
b001011 +
13
#765
#766
03
#767
#768
b001100 +
13
#769
#770
03
#771
#772
b001101 +
13
#773
#774
03
#775
#776
b001110 +
13
#777
#778
03
#779
#780
1#
b000000 +
13
1C
#781
#782
03
#783
#784
b000001 +
13
#785
#786
03
#787
#788
b000010 +
13
#789
#790
03
#791
#792
b000011 +
13
#793
#794
03
#795
#796
b000100 +
13
#797
#798
03
#799
#800
b000101 +
13
#801
#802
03
#803
#804
b000110 +
13
#805
#806
03
#807
#808
b000111 +
13
#809
#810
03
#811
#812
b001000 +
13
#813
#814
03
#815
#816
b001001 +
13
#817
#818
03
#819
#820
b001010 +
13
#821
#822
03
#823
#824
b001011 +
13
#825
#826
03
#827
#828
b001100 +
13
#829
#830
03
#831
#832
b001101 +
13
#833
#834
03
#835
#836
b001110 +
13
#837
#838
03
#839
#840
0#
b000000 +
13
0C
#841
#842
03
#843
#844
b000001 +
13
#845
#846
03
#847
#848
b000010 +
13
#849
#850
03
#851
#852
b000011 +
13
#853
#854
03
#855
#856
b000100 +
13
#857
#858
03
#859
#860
b000101 +
13
#861
#862
03
#863
#864
b000110 +
13
#865
#866
03
#867
#868
b000111 +
13
#869
#870
03
#871
#872
b001000 +
13
#873
#874
03
#875
#876
b001001 +
13
#877
#878
03
#879
#880
b001010 +
13
#881
#882
03
#883
#884
b001011 +
13
#885
#886
03
#887
#888
b001100 +
13
#889
#890
03
#891
#892
b001101 +
13
#893
#894
03
#895
#896
b001110 +
13
#897
#898
03
#899
#900
1#
b000000 +
13
1C
#901
#902
03
#903
#904
b000001 +
13
#905
#906
03
#907
#908
b000010 +
13
#909
#910
03
#911
#912
b000011 +
13
#913
#914
03
#915
#916
b000100 +
13
#917
#918
03
#919
#920
b000101 +
13
#921
#922
03
#923
#924
b000110 +
13
#925
#926
03
#927
#928
b000111 +
13
#929
#930
03
#931
#932
b001000 +
13
#933
#934
03
#935
#936
b001001 +
13
#937
#938
03
#939
#940
b001010 +
13
#941
#942
03
#943
#944
b001011 +
13
#945
#946
03
#947
#948
b001100 +
13
#949
#950
03
#951
#952
b001101 +
13
#953
#954
03
#955
#956
b001110 +
13
#957
#958
03
#959
#960
0#
b000000 +
13
0C
#961
#962
03
#963
#964
b000001 +
13
#965
#966
03
#967
#968
b000010 +
13
#969
#970
03
#971
#972
b000011 +
13
#973
#974
03
#975
#976
b000100 +
13
#977
#978
03
#979
#980
b000101 +
13
#981
#982
03
#983
#984
b000110 +
13
#985
#986
03
#987
#988
b000111 +
13
#989
#990
03
#991
#992
b001000 +
13
#993
#994
03
#995
#996
b001001 +
13
#997
#998
03
#999
#1000
b001010 +
13
#1001
#1002
03
#1003
#1004
b001011 +
13
#1005
#1006
03
#1007
#1008
b001100 +
13
#1009
#1010
03
#1011
#1012
b001101 +
13
#1013
#1014
03
#1015
#1016
b001110 +
13
#1017
#1018
03
#1019
#1020
1#
b000000 +
13
1C
#1021
#1022
03
#1023
#1024
b000001 +
13
#1025
#1026
03
#1027
#1028
b000010 +
13
#1029
#1030
03
#1031
#1032
b000011 +
13
#1033
#1034
03
#1035
#1036
b000100 +
13
#1037
#1038
03
#1039
#1040
b000101 +
13
#1041
#1042
03
#1043
#1044
b000110 +
13
#1045
#1046
03
#1047
#1048
b000111 +
13
#1049
#1050
03
#1051
#1052
b001000 +
13
#1053
#1054
03
#1055
#1056
b001001 +
13
#1057
#1058
03
#1059
#1060
b001010 +
13
#1061
#1062
03
#1063
#1064
b001011 +
13
#1065
#1066
03
#1067
#1068
b001100 +
13
#1069
#1070
03
#1071
#1072
b001101 +
13
#1073
#1074
03
#1075
#1076
b001110 +
13
#1077
#1078
03
#1079
#1080
0#
b000000 +
13
0C
#1081
#1082
03
#1083
#1084
b000001 +
13
#1085
#1086
03
#1087
#1088
b000010 +
13
#1089
#1090
03
#1091
#1092
b000011 +
13
#1093
#1094
03
#1095
#1096
b000100 +
13
#1097
#1098
03
#1099
#1100
b000101 +
13
#1101
#1102
03
#1103
#1104
b000110 +
13
#1105
#1106
03
#1107
#1108
b000111 +
13
#1109
#1110
03
#1111
#1112
b001000 +
13
#1113
#1114
03
#1115
#1116
b001001 +
13
#1117
#1118
03
#1119
#1120
b001010 +
13
#1121
#1122
03
#1123
#1124
b001011 +
13
#1125
#1126
03
#1127
#1128
b001100 +
13
#1129
#1130
03
#1131
#1132
b001101 +
13
#1133
#1134
03
#1135
#1136
b001110 +
13
#1137
#1138
03
#1139
#1140
1#
b000000 +
13
1C
#1141
#1142
03
#1143
#1144
b000001 +
13
#1145
#1146
03
#1147
#1148
b000010 +
13
#1149
#1150
03
#1151
#1152
b000011 +
13
#1153
#1154
03
#1155
#1156
b000100 +
13
#1157
#1158
03
#1159
#1160
b000101 +
13
#1161
#1162
03
#1163
#1164
b000110 +
13
#1165
#1166
03
#1167
#1168
b000111 +
13
#1169
#1170
03
#1171
#1172
b001000 +
13
#1173
#1174
03
#1175
#1176
b001001 +
13
#1177
#1178
03
#1179
#1180
b001010 +
13
#1181
#1182
03
#1183
#1184
b001011 +
13
#1185
#1186
03
#1187
#1188
b001100 +
13
#1189
#1190
03
#1191
#1192
b001101 +
13
#1193
#1194
03
#1195
#1196
b001110 +
13
#1197
#1198
03
#1199
#1200
0#
b000000 +
13
0C
#1201
#1202
03
#1203
#1204
b000001 +
13
#1205
#1206
03
#1207
#1208
b000010 +
13
#1209
#1210
03
#1211
#1212
b000011 +
13
#1213
#1214
03
#1215
#1216
b000100 +
13
#1217
#1218
03
#1219
#1220
b000101 +
13
#1221
#1222
03
#1223
#1224
b000110 +
13
#1225
#1226
03
#1227
#1228
b000111 +
13
#1229
#1230
03
#1231
#1232
b001000 +
13
#1233
#1234
03
#1235
#1236
b001001 +
13
#1237
#1238
03
#1239
#1240
b001010 +
13
#1241
#1242
03
#1243
#1244
b001011 +
13
#1245
#1246
03
#1247
#1248
b001100 +
13
#1249
#1250
03
#1251
#1252
b001101 +
13
#1253
#1254
03
#1255
#1256
b001110 +
13
#1257
#1258
03
#1259
#1260
1#
b000000 +
13
1C
#1261
#1262
03
#1263
#1264
b000001 +
13
#1265
#1266
03
#1267
#1268
b000010 +
13
#1269
#1270
03
#1271
#1272
b000011 +
13
#1273
#1274
03
#1275
#1276
b000100 +
13
#1277
#1278
03
#1279
#1280
b000101 +
13
#1281
#1282
03
#1283
#1284
b000110 +
13
#1285
#1286
03
#1287
#1288
b000111 +
13
#1289
#1290
03
#1291
#1292
b001000 +
13
#1293
#1294
03
#1295
#1296
b001001 +
13
#1297
#1298
03
#1299
#1300
b001010 +
13
#1301
#1302
03
#1303
#1304
b001011 +
13
#1305
#1306
03
#1307
#1308
b001100 +
13
#1309
#1310
03
#1311
#1312
b001101 +
13
#1313
#1314
03
#1315
#1316
b001110 +
13
#1317
#1318
03
#1319
#1320
0#
b000000 +
13
0C
#1321
#1322
03
#1323
#1324
b000001 +
13
#1325
#1326
03
#1327
#1328
b000010 +
13
#1329
#1330
03
#1331
#1332
b000011 +
13
#1333
#1334
03
#1335
#1336
b000100 +
13
#1337
#1338
03
#1339
#1340
b000101 +
13
#1341
#1342
03
#1343
#1344
b000110 +
13
#1345
#1346
03
#1347
#1348
b000111 +
13
#1349
#1350
03
#1351
#1352
b001000 +
13
#1353
#1354
03
#1355
#1356
b001001 +
13
#1357
#1358
03
#1359
#1360
b001010 +
13
#1361
#1362
03
#1363
#1364
b001011 +
13
#1365
#1366
03
#1367
#1368
b001100 +
13
#1369
#1370
03
#1371
#1372
b001101 +
13
#1373
#1374
03
#1375
#1376
b001110 +
13
#1377
#1378
03
#1379
#1380
1#
b000000 +
13
1C
#1381
#1382
03
#1383
#1384
b000001 +
13
#1385
#1386
03
#1387
#1388
b000010 +
13
#1389
#1390
03
#1391
#1392
b000011 +
13
#1393
#1394
03
#1395
#1396
b000100 +
13
#1397
#1398
03
#1399
#1400
b000101 +
13
#1401
#1402
03
#1403
#1404
b000110 +
13
#1405
#1406
03
#1407
#1408
b000111 +
13
#1409
#1410
03
#1411
#1412
b001000 +
13
#1413
#1414
03
#1415
#1416
b001001 +
13
#1417
#1418
03
#1419
#1420
b001010 +
13
#1421
#1422
03
#1423
#1424
b001011 +
13
#1425
#1426
03
#1427
#1428
b001100 +
13
#1429
#1430
03
#1431
#1432
b001101 +
13
#1433
#1434
03
#1435
#1436
b001110 +
13
#1437
#1438
03
#1439
#1440
0#
b000000 +
13
0C
#1441
#1442
03
#1443
#1444
b000001 +
13
#1445
#1446
03
#1447
#1448
b000010 +
13
#1449
#1450
03
#1451
#1452
b000011 +
13
#1453
#1454
03
#1455
#1456
b000100 +
13
#1457
#1458
03
#1459
#1460
b000101 +
13
#1461
#1462
03
#1463
#1464
b000110 +
13
#1465
#1466
03
#1467
#1468
b000111 +
13
#1469
#1470
03
#1471
#1472
b001000 +
13
#1473
#1474
03
#1475
#1476
b001001 +
13
#1477
#1478
03
#1479
#1480
b001010 +
13
#1481
#1482
03
#1483
#1484
b001011 +
13
#1485
#1486
03
#1487
#1488
b001100 +
13
#1489
#1490
03
#1491
#1492
b001101 +
13
#1493
#1494
03
#1495
#1496
b001110 +
13
#1497
#1498
03
#1499
#1500
1#
b000000 +
13
1C
#1501
#1502
03
#1503
#1504
b000001 +
13
#1505
#1506
03
#1507
#1508
b000010 +
13
#1509
#1510
03
#1511
#1512
b000011 +
13
#1513
#1514
03
#1515
#1516
b000100 +
13
#1517
#1518
03
#1519
#1520
b000101 +
13
#1521
#1522
03
#1523
#1524
b000110 +
13
#1525
#1526
03
#1527
#1528
b000111 +
13
#1529
#1530
03
#1531
#1532
b001000 +
13
#1533
#1534
03
#1535
#1536
b001001 +
13
#1537
#1538
03
#1539
#1540
b001010 +
13
#1541
#1542
03
#1543
#1544
b001011 +
13
#1545
#1546
03
#1547
#1548
b001100 +
13
#1549
#1550
03
#1551
#1552
b001101 +
13
#1553
#1554
03
#1555
#1556
b001110 +
13
#1557
#1558
03
#1559
#1560
0#
b000000 +
13
0C
#1561
#1562
03
#1563
#1564
b000001 +
13
#1565
#1566
03
#1567
#1568
b000010 +
13
#1569
#1570
03
#1571
#1572
b000011 +
13
#1573
#1574
03
#1575
#1576
b000100 +
13
#1577
#1578
03
#1579
#1580
b000101 +
13
#1581
#1582
03
#1583
#1584
b000110 +
13
#1585
#1586
03
#1587
#1588
b000111 +
13
#1589
#1590
03
#1591
#1592
b001000 +
13
#1593
#1594
03
#1595
#1596
b001001 +
13
#1597
#1598
03
#1599
#1600
b001010 +
13
#1601
#1602
03
#1603
#1604
b001011 +
13
#1605
#1606
03
#1607
#1608
b001100 +
13
#1609
#1610
03
#1611
#1612
b001101 +
13
#1613
#1614
03
#1615
#1616
b001110 +
13
#1617
#1618
03
#1619
#1620
1#
b000000 +
13
1C
#1621
#1622
03
#1623
#1624
b000001 +
13
#1625
#1626
03
#1627
#1628
b000010 +
13
#1629
#1630
03
#1631
#1632
b000011 +
13
#1633
#1634
03
#1635
#1636
b000100 +
13
#1637
#1638
03
#1639
#1640
b000101 +
13
#1641
#1642
03
#1643
#1644
b000110 +
13
#1645
#1646
03
#1647
#1648
b000111 +
13
#1649
#1650
03
#1651
#1652
b001000 +
13
#1653
#1654
03
#1655
#1656
b001001 +
13
#1657
#1658
03
#1659
#1660
b001010 +
13
#1661
#1662
03
#1663
#1664
b001011 +
13
#1665
#1666
03
#1667
#1668
b001100 +
13
#1669
#1670
03
#1671
#1672
b001101 +
13
#1673
#1674
03
#1675
#1676
b001110 +
13
#1677
#1678
03
#1679
#1680
0#
b000000 +
13
0C
#1681
#1682
03
#1683
#1684
b000001 +
13
#1685
#1686
03
#1687
#1688
b000010 +
13
#1689
#1690
03
#1691
#1692
b000011 +
13
#1693
#1694
03
#1695
#1696
b000100 +
13
#1697
#1698
03
#1699
#1700
b000101 +
13
#1701
#1702
03
#1703
#1704
b000110 +
13
#1705
#1706
03
#1707
#1708
b000111 +
13
#1709
#1710
03
#1711
#1712
b001000 +
13
#1713
#1714
03
#1715
#1716
b001001 +
13
#1717
#1718
03
#1719
#1720
b001010 +
13
#1721
#1722
03
#1723
#1724
b001011 +
13
#1725
#1726
03
#1727
#1728
b001100 +
13
#1729
#1730
03
#1731
#1732
b001101 +
13
#1733
#1734
03
#1735
#1736
b001110 +
13
#1737
#1738
03
#1739
#1740
1#
b000000 +
13
1C
#1741
#1742
03
#1743
#1744
b000001 +
13
#1745
#1746
03
#1747
#1748
b000010 +
13
#1749
#1750
03
#1751
#1752
b000011 +
13
#1753
#1754
03
#1755
#1756
b000100 +
13
#1757
#1758
03
#1759
#1760
b000101 +
13
#1761
#1762
03
#1763
#1764
b000110 +
13
#1765
#1766
03
#1767
#1768
b000111 +
13
#1769
#1770
03
#1771
#1772
b001000 +
13
#1773
#1774
03
#1775
#1776
b001001 +
13
#1777
#1778
03
#1779
#1780
b001010 +
13
#1781
#1782
03
#1783
#1784
b001011 +
13
#1785
#1786
03
#1787
#1788
b001100 +
13
#1789
#1790
03
#1791
#1792
b001101 +
13
#1793
#1794
03
#1795
#1796
b001110 +
13
#1797
#1798
03
#1799
#1800
0#
b000000 +
13
0C
#1801
#1802
03
#1803
#1804
b000001 +
13
#1805
#1806
03
#1807
#1808
b000010 +
13
#1809
#1810
03
#1811
#1812
b000011 +
13
#1813
#1814
03
#1815
#1816
b000100 +
13
#1817
#1818
03
#1819
#1820
b000101 +
13
#1821
#1822
03
#1823
#1824
b000110 +
13
#1825
#1826
03
#1827
#1828
b000111 +
13
#1829
#1830
03
#1831
#1832
b001000 +
13
#1833
#1834
03
#1835
#1836
b001001 +
13
#1837
#1838
03
#1839
#1840
b001010 +
13
#1841
#1842
03
#1843
#1844
b001011 +
13
#1845
#1846
03
#1847
#1848
b001100 +
13
#1849
#1850
03
#1851
#1852
b001101 +
13
#1853
#1854
03
#1855
#1856
b001110 +
13
#1857
#1858
03
#1859
#1860
1#
b000000 +
13
1C
#1861
#1862
03
#1863
#1864
b000001 +
13
#1865
#1866
03
#1867
#1868
b000010 +
13
#1869
#1870
03
#1871
#1872
b000011 +
13
#1873
#1874
03
#1875
#1876
b000100 +
13
#1877
#1878
03
#1879
#1880
b000101 +
13
#1881
#1882
03
#1883
#1884
b000110 +
13
#1885
#1886
03
#1887
#1888
b000111 +
13
#1889
#1890
03
#1891
#1892
b001000 +
13
#1893
#1894
03
#1895
#1896
b001001 +
13
#1897
#1898
03
#1899
#1900
b001010 +
13
#1901
#1902
03
#1903
#1904
b001011 +
13
#1905
#1906
03
#1907
#1908
b001100 +
13
#1909
#1910
03
#1911
#1912
b001101 +
13
#1913
#1914
03
#1915
#1916
b001110 +
13
#1917
#1918
03
#1919
#1920
0#
b000000 +
13
0C
#1921
#1922
03
#1923
#1924
b000001 +
13
#1925
#1926
03
#1927
#1928
b000010 +
13
#1929
#1930
03
#1931
#1932
b000011 +
13
#1933
#1934
03
#1935
#1936
b000100 +
13
#1937
#1938
03
#1939
#1940
b000101 +
13
#1941
#1942
03
#1943
#1944
b000110 +
13
#1945
#1946
03
#1947
#1948
b000111 +
13
#1949
#1950
03
#1951
#1952
b001000 +
13
#1953
#1954
03
#1955
#1956
b001001 +
13
#1957
#1958
03
#1959
#1960
b001010 +
13
#1961
#1962
03
#1963
#1964
b001011 +
13
#1965
#1966
03
#1967
#1968
b001100 +
13
#1969
#1970
03
#1971
#1972
b001101 +
13
#1973
#1974
03
#1975
#1976
b001110 +
13
#1977
#1978
03
#1979
#1980
1#
b000000 +
13
1C
#1981
#1982
03
#1983
#1984
b000001 +
13
#1985
#1986
03
#1987
#1988
b000010 +
13
#1989
#1990
03
#1991
#1992
b000011 +
13
#1993
#1994
03
#1995
#1996
b000100 +
13
#1997
#1998
03
#1999
#2000
b000101 +
13
#2001
#2002
03
#2003
#2004
b000110 +
13
#2005
#2006
03
#2007
#2008
b000111 +
13
#2009
#2010
03
#2011
#2012
b001000 +
13
#2013
#2014
03
#2015
#2016
b001001 +
13
#2017
#2018
03
#2019
#2020
b001010 +
13
#2021
#2022
03
#2023
#2024
b001011 +
13
#2025
#2026
03
#2027
#2028
b001100 +
13
#2029
#2030
03
#2031
#2032
b001101 +
13
#2033
#2034
03
#2035
#2036
b001110 +
13
#2037
#2038
03
#2039
#2040
0#
b000000 +
13
0C
#2041
#2042
03
#2043
#2044
b000001 +
13
#2045
#2046
03
#2047
#2048
b000010 +
13
#2049
#2050
03
#2051
#2052
b000011 +
13
#2053
#2054
03
#2055
#2056
b000100 +
13
#2057
#2058
03
#2059
#2060
b000101 +
13
#2061
#2062
03
#2063
#2064
b000110 +
13
#2065
#2066
03
#2067
#2068
b000111 +
13
#2069
#2070
03
#2071
#2072
b001000 +
13
#2073
#2074
03
#2075
#2076
b001001 +
13
#2077
#2078
03
#2079
#2080
b001010 +
13
#2081
#2082
03
#2083
#2084
b001011 +
13
#2085
#2086
03
#2087
#2088
b001100 +
13
#2089
#2090
03
#2091
#2092
b001101 +
13
#2093
#2094
03
#2095
#2096
b001110 +
13
#2097
#2098
03
#2099
#2100
1#
b000000 +
13
1C
#2101
#2102
03
#2103
#2104
b000001 +
13
#2105
#2106
03
#2107
#2108
b000010 +
13
#2109
#2110
03
#2111
#2112
b000011 +
13
#2113
#2114
03
#2115
#2116
b000100 +
13
#2117
#2118
03
#2119
#2120
b000101 +
13
#2121
#2122
03
#2123
#2124
b000110 +
13
#2125
#2126
03
#2127
#2128
b000111 +
13
#2129
#2130
03
#2131
#2132
b001000 +
13
#2133
#2134
03
#2135
#2136
b001001 +
13
#2137
#2138
03
#2139
#2140
b001010 +
13
#2141
#2142
03
#2143
#2144
b001011 +
13
#2145
#2146
03
#2147
#2148
b001100 +
13
#2149
#2150
03
#2151
#2152
b001101 +
13
#2153
#2154
03
#2155
#2156
b001110 +
13
#2157
#2158
03
#2159
#2160
0#
b000000 +
13
0C
#2161
#2162
03
#2163
#2164
b000001 +
13
#2165
#2166
03
#2167
#2168
b000010 +
13
#2169
#2170
03
#2171
#2172
b000011 +
13
#2173
#2174
03
#2175
#2176
b000100 +
13
#2177
#2178
03
#2179
#2180
b000101 +
13
#2181
#2182
03
#2183
#2184
b000110 +
13
#2185
#2186
03
#2187
#2188
b000111 +
13
#2189
#2190
03
#2191
#2192
b001000 +
13
#2193
#2194
03
#2195
#2196
b001001 +
13
#2197
#2198
03
#2199
#2200
b001010 +
13
#2201
#2202
03
#2203
#2204
b001011 +
13
#2205
#2206
03
#2207
#2208
b001100 +
13
#2209
#2210
03
#2211
#2212
b001101 +
13
#2213
#2214
03
#2215
#2216
b001110 +
13
#2217
#2218
03
#2219
#2220
1#
b000000 +
13
1C
#2221
#2222
03
#2223
#2224
b000001 +
13
#2225
#2226
03
#2227
#2228
b000010 +
13
#2229
#2230
03
#2231
#2232
b000011 +
13
#2233
#2234
03
#2235
#2236
b000100 +
13
#2237
#2238
03
#2239
#2240
b000101 +
13
#2241
#2242
03
#2243
#2244
b000110 +
13
#2245
#2246
03
#2247
#2248
b000111 +
13
#2249
#2250
03
#2251
#2252
b001000 +
13
#2253
#2254
03
#2255
#2256
b001001 +
13
#2257
#2258
03
#2259
#2260
b001010 +
13
#2261
#2262
03
#2263
#2264
b001011 +
13
#2265
#2266
03
#2267
#2268
b001100 +
13
#2269
#2270
03
#2271
#2272
b001101 +
13
#2273
#2274
03
#2275
#2276
b001110 +
13
#2277
#2278
03
#2279
#2280
0#
b000000 +
13
0C
#2281
#2282
03
#2283
#2284
b000001 +
13
#2285
#2286
03
#2287
#2288
b000010 +
13
#2289
#2290
03
#2291
#2292
b000011 +
13
#2293
#2294
03
#2295
#2296
b000100 +
13
#2297
#2298
03
#2299
#2300
b000101 +
13
#2301
#2302
03
#2303
#2304
b000110 +
13
#2305
#2306
03
#2307
#2308
b000111 +
13
#2309
#2310
03
#2311
#2312
b001000 +
13
#2313
#2314
03
#2315
#2316
b001001 +
13
#2317
#2318
03
#2319
#2320
b001010 +
13
#2321
#2322
03
#2323
#2324
b001011 +
13
#2325
#2326
03
#2327
#2328
b001100 +
13
#2329
#2330
03
#2331
#2332
b001101 +
13
#2333
#2334
03
#2335
#2336
b001110 +
13
#2337
#2338
03
#2339
#2340
1#
b000000 +
13
1C
#2341
#2342
03
#2343
#2344
b000001 +
13
#2345
#2346
03
#2347
#2348
b000010 +
13
