pwm/pwm.v
module pwm(clk_in, clk_out);
    input clk_in;
    output clk_out;

    reg clk_out;
    reg [2:0] state = 3'b000;
    reg [7:0] DIV = 0;
    reg [7:0] cnt = 8'b0;

    always @(negedge clk_in) begin
        if(cnt < 100 - DIV) begin
            clk_out <= 1'b0;
            cnt = cnt + 1;
        end else begin
            clk_out <= 1'b1;
            cnt = cnt + 1;
        end

        if(cnt == 99) begin
            cnt <= 0;
            case(state)
                3'b000: begin
                DIV <= 0;
                state <= state + 1;
                end
                3'b001: begin
                DIV <= 100;
                state <= state + 1;
                end
                3'b010: begin
                DIV <= 40;
                state <= state + 1;
                end
                3'b011: begin
                DIV <= 80;
                state <= state + 1;
                end
                3'b100: begin
                DIV <= 40;
                state <= state + 1;
                end
                3'b101: begin
                DIV <= 20;
                state <= state + 1;
                end
                3'b110: begin
                DIV <= 10;
                state <= state + 1;
                end
                3'b111: begin
                DIV <= 0;
                state <= state + 1;
                end
            endcase
        end
    end
endmodule

pwm/sim.v
module sim();
    reg clk_in = 0;
    wire clk_out;

    initial begin
        $dumpfile("wave.vcd");
        $dumpvars(0, pwm);
    end

    pwm pwm(clk_in, clk_out);

    always #1 begin
        clk_in = ~clk_in;
    end

    initial begin
        #7000
        $finish;
    end
endmodule

pwm/wave.vcd
$date
	Fri Nov  1 19:51:29 2019
$end
$version
	Icarus Verilog
$end
$timescale
	1s
$end
$scope module sim $end
$scope module pwm $end
$var wire 1 ! clk_in $end
$var reg 8 " DIV [7:0] $end
$var reg 1 # clk_out $end
$var reg 8 $ cnt [7:0] $end
$var reg 3 % state [2:0] $end
$upscope $end
$upscope $end
$enddefinitions $end
#0
$dumpvars
b0 %
b1 $
0#
b0 "
0!
$end
#1
1!
#2
b10 $
0!
#3
1!
#4
b11 $
0!
#5
1!
#6
b100 $
0!
#7
1!
#8
b101 $
0!
#9
1!
#10
b110 $
0!
#11
1!
#12
b111 $
0!
#13
1!
#14
b1000 $
0!
#15
1!
#16
b1001 $
0!
#17
1!
#18
b1010 $
0!
#19
1!
#20
b1011 $
0!
#21
1!
#22
b1100 $
0!
#23
1!
#24
b1101 $
0!
#25
1!
#26
b1110 $
0!
#27
1!
#28
b1111 $
0!
#29
1!
#30
b10000 $
0!
#31
1!
#32
b10001 $
0!
#33
1!
#34
b10010 $
0!
#35
1!
#36
b10011 $
0!
#37
1!
#38
b10100 $
0!
#39
1!
#40
b10101 $
0!
#41
1!
#42
b10110 $
0!
#43
1!
#44
b10111 $
0!
#45
1!
#46
b11000 $
0!
#47
1!
#48
b11001 $
0!
#49
1!
#50
b11010 $
0!
#51
1!
#52
b11011 $
0!
#53
1!
#54
b11100 $
0!
#55
1!
#56
b11101 $
0!
#57
1!
#58
b11110 $
0!
#59
1!
#60
b11111 $
0!
#61
1!
#62
b100000 $
0!
#63
1!
#64
b100001 $
0!
#65
1!
#66
b100010 $
0!
#67
1!
#68
b100011 $
0!
#69
1!
#70
b100100 $
0!
#71
1!
#72
b100101 $
0!
#73
1!
#74
b100110 $
0!
#75
1!
#76
b100111 $
0!
#77
1!
#78
b101000 $
0!
#79
1!
#80
b101001 $
0!
#81
1!
#82
b101010 $
0!
#83
1!
#84
b101011 $
0!
#85
1!
#86
b101100 $
0!
#87
1!
#88
b101101 $
0!
#89
1!
#90
b101110 $
0!
#91
1!
#92
b101111 $
0!
#93
1!
#94
b110000 $
0!
#95
1!
#96
b110001 $
0!
#97
1!
#98
b110010 $
0!
#99
1!
#100
b110011 $
0!
#101
1!
#102
b110100 $
0!
#103
1!
#104
b110101 $
0!
#105
1!
#106
b110110 $
0!
#107
1!
#108
b110111 $
0!
#109
1!
#110
b111000 $
0!
#111
1!
#112
b111001 $
0!
#113
1!
#114
b111010 $
0!
#115
1!
#116
b111011 $
0!
#117
1!
#118
b111100 $
0!
#119
1!
#120
b111101 $
0!
#121
1!
#122
b111110 $
0!
#123
1!
#124
b111111 $
0!
#125
1!
#126
b1000000 $
0!
#127
1!
#128
b1000001 $
0!
#129
1!
#130
b1000010 $
0!
#131
1!
#132
b1000011 $
0!
#133
1!
#134
b1000100 $
0!
#135
1!
#136
b1000101 $
0!
#137
1!
#138
b1000110 $
0!
#139
1!
#140
b1000111 $
0!
#141
1!
#142
b1001000 $
0!
#143
1!
#144
b1001001 $
0!
#145
1!
#146
b1001010 $
0!
#147
1!
#148
b1001011 $
0!
#149
1!
#150
b1001100 $
0!
#151
1!
#152
b1001101 $
0!
#153
1!
#154
b1001110 $
0!
#155
1!
#156
b1001111 $
0!
#157
1!
#158
b1010000 $
0!
#159
1!
#160
b1010001 $
0!
#161
1!
#162
b1010010 $
0!
#163
1!
#164
b1010011 $
0!
#165
1!
#166
b1010100 $
0!
#167
1!
#168
b1010101 $
0!
#169
1!
#170
b1010110 $
0!
#171
1!
#172
b1010111 $
0!
#173
1!
#174
b1011000 $
0!
#175
1!
#176
b1011001 $
0!
#177
1!
#178
b1011010 $
0!
#179
1!
#180
b1011011 $
0!
#181
1!
#182
b1011100 $
0!
#183
1!
#184
b1011101 $
0!
#185
1!
#186
b1011110 $
0!
#187
1!
#188
b1011111 $
0!
#189
1!
#190
b1100000 $
0!
#191
1!
#192
b1100001 $
0!
#193
1!
#194
b1100010 $
0!
#195
1!
#196
b1 %
b0 $
0!
#197
1!
#198
b1 $
0!
#199
1!
#200
b10 $
0!
#201
1!
#202
b11 $
0!
#203
1!
#204
b100 $
0!
#205
1!
#206
b101 $
0!
#207
1!
#208
b110 $
0!
#209
1!
#210
b111 $
0!
#211
1!
#212
b1000 $
0!
#213
1!
#214
b1001 $
0!
#215
1!
#216
b1010 $
0!
#217
1!
#218
b1011 $
0!
#219
1!
#220
b1100 $
0!
#221
1!
#222
b1101 $
0!
#223
1!
#224
b1110 $
0!
#225
1!
#226
b1111 $
0!
#227
1!
#228
b10000 $
0!
#229
1!
#230
b10001 $
0!
#231
1!
#232
b10010 $
0!
#233
1!
#234
b10011 $
0!
#235
1!
#236
b10100 $
0!
#237
1!
#238
b10101 $
0!
#239
1!
#240
b10110 $
0!
#241
1!
#242
b10111 $
0!
#243
1!
#244
b11000 $
0!
#245
1!
#246
b11001 $
0!
#247
1!
#248
b11010 $
0!
#249
1!
#250
b11011 $
0!
#251
1!
#252
b11100 $
0!
#253
1!
#254
b11101 $
0!
#255
1!
#256
b11110 $
0!
#257
1!
#258
b11111 $
0!
#259
1!
#260
b100000 $
0!
#261
1!
#262
b100001 $
0!
#263
1!
#264
b100010 $
0!
#265
1!
#266
b100011 $
0!
#267
1!
#268
b100100 $
0!
#269
1!
#270
b100101 $
0!
#271
1!
#272
b100110 $
0!
#273
1!
#274
b100111 $
0!
#275
1!
#276
b101000 $
0!
#277
1!
#278
b101001 $
0!
#279
1!
#280
b101010 $
0!
#281
1!
#282
b101011 $
0!
#283
1!
#284
b101100 $
0!
#285
1!
#286
b101101 $
0!
#287
1!
#288
b101110 $
0!
#289
1!
#290
b101111 $
0!
#291
1!
#292
b110000 $
0!
#293
1!
#294
b110001 $
0!
#295
1!
#296
b110010 $
0!
#297
1!
#298
b110011 $
0!
#299
1!
#300
b110100 $
0!
#301
1!
#302
b110101 $
0!
#303
1!
#304
b110110 $
0!
#305
1!
#306
b110111 $
0!
#307
1!
#308
b111000 $
0!
#309
1!
#310
b111001 $
0!
#311
1!
#312
b111010 $
0!
#313
1!
#314
b111011 $
0!
#315
1!
#316
b111100 $
0!
#317
1!
#318
b111101 $
0!
#319
1!
#320
b111110 $
0!
#321
1!
#322
b111111 $
0!
#323
1!
#324
b1000000 $
0!
#325
1!
#326
b1000001 $
0!
#327
1!
#328
b1000010 $
0!
#329
1!
#330
b1000011 $
0!
#331
1!
#332
b1000100 $
0!
#333
1!
#334
b1000101 $
0!
#335
1!
#336
b1000110 $
0!
#337
1!
#338
b1000111 $
0!
#339
1!
#340
b1001000 $
0!
#341
1!
#342
b1001001 $
0!
#343
1!
#344
b1001010 $
0!
#345
1!
#346
b1001011 $
0!
#347
1!
#348
b1001100 $
0!
#349
1!
#350
b1001101 $
0!
#351
1!
#352
b1001110 $
0!
#353
1!
#354
b1001111 $
0!
#355
1!
#356
b1010000 $
0!
#357
1!
#358
b1010001 $
0!
#359
1!
#360
b1010010 $
0!
#361
1!
#362
b1010011 $
0!
#363
1!
#364
b1010100 $
0!
#365
1!
#366
b1010101 $
0!
#367
1!
#368
b1010110 $
0!
#369
1!
#370
b1010111 $
0!
#371
1!
#372
b1011000 $
0!
#373
1!
#374
b1011001 $
0!
#375
1!
#376
b1011010 $
0!
#377
1!
#378
b1011011 $
0!
#379
1!
#380
b1011100 $
0!
#381
1!
#382
b1011101 $
0!
#383
1!
#384
b1011110 $
0!
#385
1!
#386
b1011111 $
0!
#387
1!
#388
b1100000 $
0!
#389
1!
#390
b1100001 $
0!
#391
1!
#392
b1100010 $
0!
#393
1!
#394
b10 %
b1100100 "
b0 $
0!
#395
1!
#396
1#
b1 $
0!
#397
1!
#398
b10 $
0!
#399
1!
#400
b11 $
0!
#401
1!
#402
b100 $
0!
#403
1!
#404
b101 $
0!
#405
1!
#406
b110 $
0!
#407
1!
#408
b111 $
0!
#409
1!
#410
b1000 $
0!
#411
1!
#412
b1001 $
0!
#413
1!
#414
b1010 $
0!
#415
1!
#416
b1011 $
0!
#417
1!
#418
b1100 $
0!
#419
1!
#420
b1101 $
0!
#421
1!
#422
b1110 $
0!
#423
1!
#424
b1111 $
0!
#425
1!
#426
b10000 $
0!
#427
1!
#428
b10001 $
0!
#429
1!
#430
b10010 $
0!
#431
1!
#432
b10011 $
0!
#433
1!
#434
b10100 $
0!
#435
1!
#436
b10101 $
0!
#437
1!
#438
b10110 $
0!
#439
1!
#440
b10111 $
0!
#441
1!
#442
b11000 $
0!
#443
1!
#444
b11001 $
0!
#445
1!
#446
b11010 $
0!
#447
1!
#448
b11011 $
0!
#449
1!
#450
b11100 $
0!
#451
1!
#452
b11101 $
0!
#453
1!
#454
b11110 $
0!
#455
1!
#456
b11111 $
0!
#457
1!
#458
b100000 $
0!
#459
1!
#460
b100001 $
0!
#461
1!
#462
b100010 $
0!
#463
1!
#464
b100011 $
0!
#465
1!
#466
b100100 $
0!
#467
1!
#468
b100101 $
0!
#469
1!
#470
b100110 $
0!
#471
1!
#472
b100111 $
0!
#473
1!
#474
b101000 $
0!
#475
1!
#476
b101001 $
0!
#477
1!
#478
b101010 $
0!
#479
1!
#480
b101011 $
0!
#481
1!
#482
b101100 $
0!
#483
1!
#484
b101101 $
0!
#485
1!
#486
b101110 $
0!
#487
1!
#488
b101111 $
0!
#489
1!
#490
b110000 $
0!
#491
1!
#492
b110001 $
0!
#493
1!
#494
b110010 $
0!
#495
1!
#496
b110011 $
0!
#497
1!
#498
b110100 $
0!
#499
1!
#500
b110101 $
0!
#501
1!
#502
b110110 $
0!
#503
1!
#504
b110111 $
0!
#505
1!
#506
b111000 $
0!
#507
1!
#508
b111001 $
0!
#509
1!
#510
b111010 $
0!
#511
1!
#512
b111011 $
0!
#513
1!
#514
b111100 $
0!
#515
1!
#516
b111101 $
0!
#517
1!
#518
b111110 $
0!
#519
1!
#520
b111111 $
0!
#521
1!
#522
b1000000 $
0!
#523
1!
#524
b1000001 $
0!
#525
1!
#526
b1000010 $
0!
#527
1!
#528
b1000011 $
0!
#529
1!
#530
b1000100 $
0!
#531
1!
#532
b1000101 $
0!
#533
1!
#534
b1000110 $
0!
#535
1!
#536
b1000111 $
0!
#537
1!
#538
b1001000 $
0!
#539
1!
#540
b1001001 $
0!
#541
1!
#542
b1001010 $
0!
#543
1!
#544
b1001011 $
0!
#545
1!
#546
b1001100 $
0!
#547
1!
#548
b1001101 $
0!
#549
1!
#550
b1001110 $
0!
#551
1!
#552
b1001111 $
0!
#553
1!
#554
b1010000 $
0!
#555
1!
#556
b1010001 $
0!
#557
1!
#558
b1010010 $
0!
#559
1!
#560
b1010011 $
0!
#561
1!
#562
b1010100 $
0!
#563
1!
#564
b1010101 $
0!
#565
1!
#566
b1010110 $
0!
#567
1!
#568
b1010111 $
0!
#569
1!
#570
b1011000 $
0!
#571
1!
#572
b1011001 $
0!
#573
1!
#574
b1011010 $
0!
#575
1!
#576
b1011011 $
0!
#577
1!
#578
b1011100 $
0!
#579
1!
#580
b1011101 $
0!
#581
1!
#582
b1011110 $
0!
#583
1!
#584
b1011111 $
0!
#585
1!
#586
b1100000 $
0!
#587
1!
#588
b1100001 $
0!
#589
1!
#590
b1100010 $
0!
#591
1!
#592
b11 %
b101000 "
b0 $
0!
#593
1!
#594
0#
b1 $
0!
#595
1!
#596
b10 $
0!
#597
1!
#598
b11 $
0!
#599
1!
#600
b100 $
0!
#601
1!
#602
b101 $
0!
#603
1!
#604
b110 $
0!
#605
1!
#606
b111 $
0!
#607
1!
#608
b1000 $
0!
#609
1!
#610
b1001 $
0!
#611
1!
#612
b1010 $
0!
#613
1!
#614
b1011 $
0!
#615
1!
#616
b1100 $
0!
#617
1!
#618
b1101 $
0!
#619
1!
#620
b1110 $
0!
#621
1!
#622
b1111 $
0!
#623
1!
#624
b10000 $
0!
#625
1!
#626
b10001 $
0!
#627
1!
#628
b10010 $
0!
#629
1!
#630
b10011 $
0!
#631
1!
#632
b10100 $
0!
#633
1!
#634
b10101 $
0!
#635
1!
#636
b10110 $
0!
#637
1!
#638
b10111 $
0!
#639
1!
#640
b11000 $
0!
#641
1!
#642
b11001 $
0!
#643
1!
#644
b11010 $
0!
#645
1!
#646
b11011 $
0!
#647
1!
#648
b11100 $
0!
#649
1!
#650
b11101 $
0!
#651
1!
#652
b11110 $
0!
#653
1!
#654
b11111 $
0!
#655
1!
#656
b100000 $
0!
#657
1!
#658
b100001 $
0!
#659
1!
#660
b100010 $
0!
#661
1!
#662
b100011 $
0!
#663
1!
#664
b100100 $
0!
#665
1!
#666
b100101 $
0!
#667
1!
#668
b100110 $
0!
#669
1!
#670
b100111 $
0!
#671
1!
#672
b101000 $
0!
#673
1!
#674
b101001 $
0!
#675
1!
#676
b101010 $
0!
#677
1!
#678
b101011 $
0!
#679
1!
#680
b101100 $
0!
#681
1!
#682
b101101 $
0!
#683
1!
#684
b101110 $
0!
#685
1!
#686
b101111 $
0!
#687
1!
#688
b110000 $
0!
#689
1!
#690
b110001 $
0!
#691
1!
#692
b110010 $
0!
#693
1!
#694
b110011 $
0!
#695
1!
#696
b110100 $
0!
#697
1!
#698
b110101 $
0!
#699
1!
#700
b110110 $
0!
#701
1!
#702
b110111 $
0!
#703
1!
#704
b111000 $
0!
#705
1!
#706
b111001 $
0!
#707
1!
#708
b111010 $
0!
#709
1!
#710
b111011 $
0!
#711
1!
#712
b111100 $
0!
#713
1!
#714
1#
b111101 $
0!
#715
1!
#716
b111110 $
0!
#717
1!
#718
b111111 $
0!
#719
1!
#720
b1000000 $
0!
#721
1!
#722
b1000001 $
0!
#723
1!
#724
b1000010 $
0!
#725
1!
#726
b1000011 $
0!
#727
1!
#728
b1000100 $
0!
#729
1!
#730
b1000101 $
0!
#731
1!
#732
b1000110 $
0!
#733
1!
#734
b1000111 $
0!
#735
1!
#736
b1001000 $
0!
#737
1!
#738
b1001001 $
0!
#739
1!
#740
b1001010 $
0!
#741
1!
#742
b1001011 $
0!
#743
1!
#744
b1001100 $
0!
#745
1!
#746
b1001101 $
0!
#747
1!
#748
b1001110 $
0!
#749
1!
#750
b1001111 $
0!
#751
1!
#752
b1010000 $
0!
#753
1!
#754
b1010001 $
0!
#755
1!
#756
b1010010 $
0!
#757
1!
#758
b1010011 $
0!
#759
1!
#760
b1010100 $
0!
#761
1!
#762
b1010101 $
0!
#763
1!
#764
b1010110 $
0!
#765
1!
#766
b1010111 $
0!
#767
1!
#768
b1011000 $
0!
#769
1!
#770
b1011001 $
0!
#771
1!
#772
b1011010 $
0!
#773
1!
#774
b1011011 $
0!
#775
1!
#776
b1011100 $
0!
#777
1!
#778
b1011101 $
0!
#779
1!
#780
b1011110 $
0!
#781
1!
#782
b1011111 $
0!
#783
1!
#784
b1100000 $
0!
#785
1!
#786
b1100001 $
0!
#787
1!
#788
b1100010 $
0!
#789
1!
#790
b100 %
b1010000 "
b0 $
0!
#791
1!
#792
0#
b1 $
0!
#793
1!
#794
b10 $
0!
#795
1!
#796
b11 $
0!
#797
1!
#798
b100 $
0!
#799
1!
#800
b101 $
0!
#801
1!
#802
b110 $
0!
#803
1!
#804
b111 $
0!
#805
1!
#806
b1000 $
0!
#807
1!
#808
b1001 $
0!
#809
1!
#810
b1010 $
0!
#811
1!
#812
b1011 $
0!
#813
1!
#814
b1100 $
0!
#815
1!
#816
b1101 $
0!
#817
1!
#818
b1110 $
0!
#819
1!
#820
b1111 $
0!
#821
1!
#822
b10000 $
0!
#823
1!
#824
b10001 $
0!
#825
1!
#826
b10010 $
0!
#827
1!
#828
b10011 $
0!
#829
1!
#830
b10100 $
0!
#831
1!
#832
1#
b10101 $
0!
#833
1!
#834
b10110 $
0!
#835
1!
#836
b10111 $
0!
#837
1!
#838
b11000 $
0!
#839
1!
#840
b11001 $
0!
#841
1!
#842
b11010 $
0!
#843
1!
#844
b11011 $
0!
#845
1!
#846
b11100 $
0!
#847
1!
#848
b11101 $
0!
#849
1!
#850
b11110 $
0!
#851
1!
#852
b11111 $
0!
#853
1!
#854
b100000 $
0!
#855
1!
#856
b100001 $
0!
#857
1!
#858
b100010 $
0!
#859
1!
#860
b100011 $
0!
#861
1!
#862
b100100 $
0!
#863
1!
#864
b100101 $
0!
#865
1!
#866
b100110 $
0!
#867
1!
#868
b100111 $
0!
#869
1!
#870
b101000 $
0!
#871
1!
#872
b101001 $
0!
#873
1!
#874
b101010 $
0!
#875
1!
#876
b101011 $
0!
#877
1!
#878
b101100 $
0!
#879
1!
#880
b101101 $
0!
#881
1!
#882
b101110 $
0!
#883
1!
#884
b101111 $
0!
#885
1!
#886
b110000 $
0!
#887
1!
#888
b110001 $
0!
#889
1!
#890
b110010 $
0!
#891
1!
#892
b110011 $
0!
#893
1!
#894
b110100 $
0!
#895
1!
#896
b110101 $
0!
#897
1!
#898
b110110 $
0!
#899
1!
#900
b110111 $
0!
#901
1!
#902
b111000 $
0!
#903
1!
#904
b111001 $
0!
#905
1!
#906
b111010 $
0!
#907
1!
#908
b111011 $
0!
#909
1!
#910
b111100 $
0!
#911
1!
#912
b111101 $
0!
#913
1!
#914
b111110 $
0!
#915
1!
#916
b111111 $
0!
#917
1!
#918
b1000000 $
0!
#919
1!
#920
b1000001 $
0!
#921
1!
#922
b1000010 $
0!
#923
1!
#924
b1000011 $
0!
#925
1!
#926
b1000100 $
0!
#927
1!
#928
b1000101 $
0!
#929
1!
#930
b1000110 $
0!
#931
1!
#932
b1000111 $
0!
#933
1!
#934
b1001000 $
0!
#935
1!
#936
b1001001 $
0!
#937
1!
#938
b1001010 $
0!
#939
1!
#940
b1001011 $
0!
#941
1!
#942
b1001100 $
0!
#943
1!
#944
b1001101 $
0!
#945
1!
#946
b1001110 $
0!
#947
1!
#948
b1001111 $
0!
#949
1!
#950
b1010000 $
0!
#951
1!
#952
b1010001 $
0!
#953
1!
#954
b1010010 $
0!
#955
1!
#956
b1010011 $
0!
#957
1!
#958
b1010100 $
0!
#959
1!
#960
b1010101 $
0!
#961
1!
#962
b1010110 $
0!
#963
1!
#964
b1010111 $
0!
#965
1!
#966
b1011000 $
0!
#967
1!
#968
b1011001 $
0!
#969
1!
#970
b1011010 $
0!
#971
1!
#972
b1011011 $
0!
#973
1!
#974
b1011100 $
0!
#975
1!
#976
b1011101 $
0!
#977
1!
#978
b1011110 $
0!
#979
1!
#980
b1011111 $
0!
#981
1!
#982
b1100000 $
0!
#983
1!
#984
b1100001 $
0!
#985
1!
#986
b1100010 $
0!
#987
1!
#988
b101 %
b101000 "
b0 $
0!
#989
1!
#990
0#
b1 $
0!
#991
1!
#992
b10 $
0!
#993
1!
#994
b11 $
0!
#995
1!
#996
b100 $
0!
#997
1!
#998
b101 $
0!
#999
1!
#1000
b110 $
0!
#1001
1!
#1002
b111 $
0!
#1003
1!
#1004
b1000 $
0!
#1005
1!
#1006
b1001 $
0!
#1007
1!
#1008
b1010 $
0!
#1009
1!
#1010
b1011 $
0!
#1011
1!
#1012
b1100 $
0!
#1013
1!
#1014
b1101 $
0!
#1015
1!
#1016
b1110 $
0!
#1017
1!
#1018
b1111 $
0!
#1019
1!
#1020
b10000 $
0!
#1021
1!
#1022
b10001 $
0!
#1023
1!
#1024
b10010 $
0!
#1025
1!
#1026
b10011 $
0!
#1027
1!
#1028
b10100 $
0!
#1029
1!
#1030
b10101 $
0!
#1031
1!
#1032
b10110 $
0!
#1033
1!
#1034
b10111 $
0!
#1035
1!
#1036
b11000 $
0!
#1037
1!
#1038
b11001 $
0!
#1039
1!
#1040
b11010 $
0!
#1041
1!
#1042
b11011 $
0!
#1043
1!
#1044
b11100 $
0!
#1045
1!
#1046
b11101 $
0!
#1047
1!
#1048
b11110 $
0!
#1049
1!
#1050
b11111 $
0!
#1051
1!
#1052
b100000 $
0!
#1053
1!
#1054
b100001 $
0!
#1055
1!
#1056
b100010 $
0!
#1057
1!
#1058
b100011 $
0!
#1059
1!
#1060
b100100 $
0!
#1061
1!
#1062
b100101 $
0!
#1063
1!
#1064
b100110 $
0!
#1065
1!
#1066
b100111 $
0!
#1067
1!
#1068
b101000 $
0!
#1069
1!
#1070
b101001 $
0!
#1071
1!
#1072
b101010 $
0!
#1073
1!
#1074
b101011 $
0!
#1075
1!
#1076
b101100 $
0!
#1077
1!
#1078
b101101 $
0!
#1079
1!
#1080
b101110 $
0!
#1081
1!
#1082
b101111 $
0!
#1083
1!
#1084
b110000 $
0!
#1085
1!
#1086
b110001 $
0!
#1087
1!
#1088
b110010 $
0!
#1089
1!
#1090
b110011 $
0!
#1091
1!
#1092
b110100 $
0!
#1093
1!
#1094
b110101 $
0!
#1095
1!
#1096
b110110 $
0!
#1097
1!
#1098
b110111 $
0!
#1099
1!
#1100
b111000 $
0!
#1101
1!
#1102
b111001 $
0!
#1103
1!
#1104
b111010 $
0!
#1105
1!
#1106
b111011 $
0!
#1107
1!
#1108
b111100 $
0!
#1109
1!
#1110
1#
b111101 $
0!
#1111
1!
#1112
b111110 $
0!
#1113
1!
#1114
b111111 $
0!
#1115
1!
#1116
b1000000 $
0!
#1117
1!
#1118
b1000001 $
0!
#1119
1!
#1120
b1000010 $
0!
#1121
1!
#1122
b1000011 $
0!
#1123
1!
#1124
b1000100 $
0!
#1125
1!
#1126
b1000101 $
0!
#1127
1!
#1128
b1000110 $
0!
#1129
1!
#1130
b1000111 $
0!
#1131
1!
#1132
b1001000 $
0!
#1133
1!
#1134
b1001001 $
0!
#1135
1!
#1136
b1001010 $
0!
#1137
1!
#1138
b1001011 $
0!
#1139
1!
#1140
b1001100 $
0!
#1141
1!
#1142
b1001101 $
0!
#1143
1!
#1144
b1001110 $
0!
#1145
1!
#1146
b1001111 $
0!
#1147
1!
#1148
b1010000 $
0!
#1149
1!
#1150
b1010001 $
0!
#1151
1!
#1152
b1010010 $
0!
#1153
1!
#1154
b1010011 $
0!
#1155
1!
#1156
b1010100 $
0!
#1157
1!
#1158
b1010101 $
0!
#1159
1!
#1160
b1010110 $
0!
#1161
1!
#1162
b1010111 $
0!
#1163
1!
#1164
b1011000 $
0!
#1165
1!
#1166
b1011001 $
0!
#1167
1!
#1168
b1011010 $
0!
#1169
1!
#1170
b1011011 $
0!
#1171
1!
#1172
b1011100 $
0!
#1173
1!
#1174
b1011101 $
0!
#1175
1!
#1176
b1011110 $
0!
#1177
1!
#1178
b1011111 $
0!
#1179
1!
#1180
b1100000 $
0!
#1181
1!
#1182
b1100001 $
0!
#1183
1!
#1184
b1100010 $
0!
#1185
1!
#1186
b110 %
b10100 "
b0 $
0!
#1187
1!
#1188
0#
b1 $
0!
#1189
1!
#1190
b10 $
0!
#1191
1!
#1192
b11 $
0!
#1193
1!
#1194
b100 $
0!
#1195
1!
#1196
b101 $
0!
#1197
1!
#1198
b110 $
0!
#1199
1!
#1200
b111 $
0!
#1201
1!
#1202
b1000 $
0!
#1203
1!
#1204
b1001 $
0!
#1205
1!
#1206
b1010 $
0!
#1207
1!
#1208
b1011 $
0!
#1209
1!
#1210
b1100 $
0!
#1211
1!
#1212
b1101 $
0!
#1213
1!
#1214
b1110 $
0!
#1215
1!
#1216
b1111 $
0!
#1217
1!
#1218
b10000 $
0!
#1219
1!
#1220
b10001 $
0!
#1221
1!
#1222
b10010 $
0!
#1223
1!
#1224
b10011 $
0!
#1225
1!
#1226
b10100 $
0!
#1227
1!
#1228
b10101 $
0!
#1229
1!
#1230
b10110 $
0!
#1231
1!
#1232
b10111 $
0!
#1233
1!
#1234
b11000 $
0!
#1235
1!
#1236
b11001 $
0!
#1237
1!
#1238
b11010 $
0!
#1239
1!
#1240
b11011 $
0!
#1241
1!
#1242
b11100 $
0!
#1243
1!
#1244
b11101 $
0!
#1245
1!
#1246
b11110 $
0!
#1247
1!
#1248
b11111 $
0!
#1249
1!
#1250
b100000 $
0!
#1251
1!
#1252
b100001 $
0!
#1253
1!
#1254
b100010 $
0!
#1255
1!
#1256
b100011 $
0!
#1257
1!
#1258
b100100 $
0!
#1259
1!
#1260
b100101 $
0!
#1261
1!
#1262
b100110 $
0!
#1263
1!
#1264
b100111 $
0!
#1265
1!
#1266
b101000 $
0!
#1267
1!
#1268
b101001 $
0!
#1269
1!
#1270
b101010 $
0!
#1271
1!
#1272
b101011 $
0!
#1273
1!
#1274
b101100 $
0!
#1275
1!
#1276
b101101 $
0!
#1277
1!
#1278
b101110 $
0!
#1279
1!
#1280
b101111 $
0!
#1281
1!
#1282
b110000 $
0!
#1283
1!
#1284
b110001 $
0!
#1285
1!
#1286
b110010 $
0!
#1287
1!
#1288
b110011 $
0!
#1289
1!
#1290
b110100 $
0!
#1291
1!
#1292
b110101 $
0!
#1293
1!
#1294
b110110 $
0!
#1295
1!
#1296
b110111 $
0!
#1297
1!
#1298
b111000 $
0!
#1299
1!
#1300
b111001 $
0!
#1301
1!
#1302
b111010 $
0!
#1303
1!
#1304
b111011 $
0!
#1305
1!
#1306
b111100 $
0!
#1307
1!
#1308
b111101 $
0!
#1309
1!
#1310
b111110 $
0!
#1311
1!
#1312
b111111 $
0!
#1313
1!
#1314
b1000000 $
0!
#1315
1!
#1316
b1000001 $
0!
#1317
1!
#1318
b1000010 $
0!
#1319
1!
#1320
b1000011 $
0!
#1321
1!
#1322
b1000100 $
0!
#1323
1!
#1324
b1000101 $
0!
#1325
1!
#1326
b1000110 $
0!
#1327
1!
#1328
b1000111 $
0!
#1329
1!
#1330
b1001000 $
0!
#1331
1!
#1332
b1001001 $
0!
#1333
1!
#1334
b1001010 $
0!
#1335
1!
#1336
b1001011 $
0!
#1337
1!
#1338
b1001100 $
0!
#1339
1!
#1340
b1001101 $
0!
#1341
1!
#1342
b1001110 $
0!
#1343
1!
#1344
b1001111 $
0!
#1345
1!
#1346
b1010000 $
0!
#1347
1!
#1348
1#
b1010001 $
0!
#1349
1!
#1350
b1010010 $
0!
#1351
1!
#1352
b1010011 $
0!
#1353
1!
#1354
b1010100 $
0!
#1355
1!
#1356
b1010101 $
0!
#1357
1!
#1358
b1010110 $
0!
#1359
1!
#1360
b1010111 $
0!
#1361
1!
#1362
b1011000 $
0!
#1363
1!
#1364
b1011001 $
0!
#1365
1!
#1366
b1011010 $
0!
#1367
1!
#1368
b1011011 $
0!
#1369
1!
#1370
b1011100 $
0!
#1371
1!
#1372
b1011101 $
0!
#1373
1!
#1374
b1011110 $
0!
#1375
1!
#1376
b1011111 $
0!
#1377
1!
#1378
b1100000 $
0!
#1379
1!
#1380
b1100001 $
0!
#1381
1!
#1382
b1100010 $
0!
#1383
1!
#1384
b111 %
b1010 "
b0 $
0!
#1385
1!
#1386
0#
b1 $
0!
#1387
1!
#1388
b10 $
0!
#1389
1!
#1390
b11 $
0!
#1391
1!
#1392
b100 $
0!
#1393
1!
#1394
b101 $
0!
#1395
1!
#1396
b110 $
0!
#1397
1!
#1398
b111 $
0!
#1399
1!
#1400
b1000 $
0!
#1401
1!
#1402
b1001 $
0!
#1403
1!
#1404
b1010 $
0!
#1405
1!
#1406
b1011 $
0!
#1407
1!
#1408
b1100 $
0!
#1409
1!
#1410
b1101 $
0!
#1411
1!
#1412
b1110 $
0!
#1413
1!
#1414
b1111 $
0!
#1415
1!
#1416
b10000 $
0!
#1417
1!
#1418
b10001 $
0!
#1419
1!
#1420
b10010 $
0!
#1421
1!
#1422
b10011 $
0!
#1423
1!
#1424
b10100 $
0!
#1425
1!
#1426
b10101 $
0!
#1427
1!
#1428
b10110 $
0!
#1429
1!
#1430
b10111 $
0!
#1431
1!
#1432
b11000 $
0!
#1433
1!
#1434
b11001 $
0!
#1435
1!
#1436
b11010 $
0!
#1437
1!
#1438
b11011 $
0!
#1439
1!
#1440
b11100 $
0!
#1441
1!
#1442
b11101 $
0!
#1443
1!
#1444
b11110 $
0!
#1445
1!
#1446
b11111 $
0!
#1447
1!
#1448
b100000 $
0!
#1449
1!
#1450
b100001 $
0!
#1451
1!
#1452
b100010 $
0!
#1453
1!
#1454
b100011 $
0!
#1455
1!
#1456
b100100 $
0!
#1457
1!
#1458
b100101 $
0!
#1459
1!
#1460
b100110 $
0!
#1461
1!
#1462
b100111 $
0!
#1463
1!
#1464
b101000 $
0!
#1465
1!
#1466
b101001 $
0!
#1467
1!
#1468
b101010 $
0!
#1469
1!
#1470
b101011 $
0!
#1471
1!
#1472
b101100 $
0!
#1473
1!
#1474
b101101 $
0!
#1475
1!
#1476
b101110 $
0!
#1477
1!
#1478
b101111 $
0!
#1479
1!
#1480
b110000 $
0!
#1481
1!
#1482
b110001 $
0!
#1483
1!
#1484
b110010 $
0!
